pygame_animation_player/__init__.py
pygame_animation_player/animation.py
pygame_animation_player/animation_player.py
pygame_animation_player-1.0.4.dist-info/licenses/LICENSE
pygame_animation_player-1.0.4.dist-info/METADATA
pygame_animation_player-1.0.4.dist-info/WHEEL
pygame_animation_player-1.0.4.dist-info/top_level.txt
pygame_animation_player-1.0.4.dist-info/RECORD
