Metadata-Version: 2.4
Name: pygame-animation-player
Version: 1.0.4
Summary: A simple animation player for pygame sprites
Author-email: de-dust-enjoyer <dedustenjoyer@gmail.com>
License: MIT
Project-URL: Homepage, https://github.com/de-dust-enjoyer/pygame-animation-player
Project-URL: Bug Reports, https://github.com/de-dust-enjoyer/pygame-animation-player/issues
Project-URL: Source, https://github.com/de-dust-enjoyer/pygame-animation-player
Keywords: pygame,animation,sprites,game development
Classifier: Development Status :: 4 - Beta
Classifier: Intended Audience :: Developers
Classifier: License :: OSI Approved :: MIT License
Classifier: Programming Language :: Python :: 3
Classifier: Programming Language :: Python :: 3.8
Classifier: Programming Language :: Python :: 3.9
Classifier: Programming Language :: Python :: 3.10
Classifier: Programming Language :: Python :: 3.11
Classifier: Topic :: Games/Entertainment
Classifier: Topic :: Software Development :: Libraries :: pygame
Requires-Python: >=3.8
License-File: LICENSE
Requires-Dist: pygame-ce>=2.0.0
Provides-Extra: dev
Requires-Dist: pytest>=7.0; extra == "dev"
Requires-Dist: black; extra == "dev"
Requires-Dist: mypy; extra == "dev"
Requires-Dist: flake8; extra == "dev"
Dynamic: license-file
